Package_Mehdi/Mehdi.py
Package_Mehdi/__init__.py
package_mehdi-0.0.4.dist-info/METADATA
package_mehdi-0.0.4.dist-info/WHEEL
package_mehdi-0.0.4.dist-info/top_level.txt
package_mehdi-0.0.4.dist-info/RECORD
