Metadata-Version: 2.4
Name: Package_Mehdi
Version: 0.0.4
Summary: Un package minimal
Requires-Python: >=3.7
